{
  "name": "IfNickel",
  "version": "1.2.0",
  "title": "If I Had A Nickel",
  "author": "planetfall",
  "homepage": "",
  "description": "Updated to 2.0. Adds nickel ore and plates, invar alloy, and some mechanical components.",
  "factorio_version": "2.0",
  "dependencies": ["base >= 2.0", "? bzlead", "? bzaluminum", "? bzcarbon", "? bzfoundry", "? bztin", "? bztungsten", "? BrassTacks >= 1.1", "? bzgold", 
  "?manganese", "? space-exploration", "? aai-industry", "? deadlock-beltboxes-loaders", "? DeadlockCrating", "? Krastorio2", "? FluidMustFlow", "? Expensive_Fluid_Must_Flow_Recipes", "? 248k", "? LunarLandings"]
}
